Metadata-Version: 1.1
Name: the_matrix
Version: 0.2.7
Summary: Module to control Boldport "The Matrix"
Home-page: https://github.cm/threebytesfull.com/the_matrix_pi
Author: Rufus Cable
Author-email: rufus@threebytesfull.com
License: MIT
Keywords: boldport led matrix i2c rpi as1130
Platform: UNKNOWN
Classifier: Development Status :: 3 - Alpha
Classifier: Intended Audience :: Developers
Classifier: Topic :: Software Development :: Embedded Systems
Classifier: License :: OSI Approved :: MIT License
Classifier: Programming Language :: Python :: 2
Classifier: Programming Language :: Python :: 2.7
Classifier: Programming Language :: Python :: 3
Classifier: Programming Language :: Python :: 3.4
Classifier: Programming Language :: Python :: 3.5
Classifier: Programming Language :: Python :: 3.6
